{"listColumn":{"about":{"name":"about","type":-1,"typeName":"LONGTEXT"},"author":{"name":"author","type":12,"typeName":"VARCHAR"},"catalog_id":{"name":"catalog_id","pk_column":"id","pk_table":"catalog","type":4,"typeName":"INT"},"chaodai":{"name":"chaodai","type":12,"typeName":"VARCHAR"},"file_name":{"name":"file_name","type":12,"typeName":"VARCHAR"},"id":{"name":"id","type":4,"typeName":"INT"},"name":{"name":"name","type":12,"typeName":"VARCHAR"},"tm_year":{"name":"tm_year","type":12,"typeName":"VARCHAR"},"type":{"name":"type","type":12,"typeName":"VARCHAR"}},"tb":"book"}